LICENSE
MANIFEST.in
README.md
setup.py
src/cypher_subgraph/__init__.py
src/cypher_subgraph/add_to_subgraph.py
src/cypher_subgraph/canonize_subgraph_id.py
src/cypher_subgraph/cli.py
src/cypher_subgraph/delete_subgraph.py
src/cypher_subgraph/parse_cypher.py
src/cypher_subgraph/py.typed
src/cypher_subgraph/rewrite_for_subgraph.py
src/cypher_subgraph/visitor_common_functions_mixin.py
src/cypher_subgraph.egg-info/PKG-INFO
src/cypher_subgraph.egg-info/SOURCES.txt
src/cypher_subgraph.egg-info/dependency_links.txt
src/cypher_subgraph.egg-info/entry_points.txt
src/cypher_subgraph.egg-info/requires.txt
src/cypher_subgraph.egg-info/top_level.txt
src/cypher_subgraph/generated/CypherLexer.py
src/cypher_subgraph/generated/CypherParser.py
src/cypher_subgraph/generated/CypherVisitor.py
src/cypher_subgraph/generated/__init__.py