Metadata-Version: 2.1
Name: cypher-subgraph
Version: 0.1.1
Summary: A python library and CLI tool that rewrites and generates cypher queries for supporting sub-graph.
Home-page: https://github.com/AlirezaRoshanzamir/cypher-subgraph/tree/main/src/cypher_subgraph
Author: Alireza Roshanzamir
Author-email: a.roshanzamir1996@gmail.com
License: MIT License
Platform: UNKNOWN
Requires-Python: >=3.7
License-File: LICENSE
